give_me_python
