Metadata-Version: 2.1
Name: give-me-python
Version: 3.9.12
Summary: CPython installable via pip
Home-page: https://github.com/jjhelmus/give-me-python
Author: Jonathan Helmus
License: UNKNOWN
Platform: UNKNOWN
